<profile>

<ReportVersion>
<Version>2019.2</Version>
</ReportVersion>

<UserAssignments>
<unit>ns</unit>
<ProductFamily>artix7</ProductFamily>
<Part>xc7a200t-fbg676-2</Part>
<TopModelName>pqcrystals_dilithium_2</TopModelName>
<TargetClockPeriod>10.00</TargetClockPeriod>
<ClockUncertainty>1.25</ClockUncertainty>
</UserAssignments>

<PerformanceEstimates>
<PipelineType>none</PipelineType>
<SummaryOfTimingAnalysis>
<unit>ns</unit>
<EstimatedClockPeriod>7.354</EstimatedClockPeriod>
</SummaryOfTimingAnalysis>
<SummaryOfOverallLatency>
<unit>clock cycles</unit>
<Best-caseLatency>2570</Best-caseLatency>
<Average-caseLatency>2570</Average-caseLatency>
<Worst-caseLatency>2570</Worst-caseLatency>
<Best-caseRealTimeLatency>25.700 us</Best-caseRealTimeLatency>
<Average-caseRealTimeLatency>25.700 us</Average-caseRealTimeLatency>
<Worst-caseRealTimeLatency>25.700 us</Worst-caseRealTimeLatency>
<Interval-min>2570</Interval-min>
<Interval-max>2570</Interval-max>
</SummaryOfOverallLatency>
<SummaryOfLoopLatency>
<Loop1>
<TripCount>32</TripCount>
<Latency>64</Latency>
<IterationLatency>2</IterationLatency>
</Loop1>
<Loop2>
<TripCount>32</TripCount>
<Latency>64</Latency>
<IterationLatency>2</IterationLatency>
</Loop2>
<Loop3>
<TripCount>48</TripCount>
<Latency>96</Latency>
<IterationLatency>2</IterationLatency>
</Loop3>
<Loop4>
<TripCount>4</TripCount>
<Latency>652</Latency>
<IterationLatency>163</IterationLatency>
</Loop4>
<Loop5>
<TripCount>4</TripCount>
<Latency>652</Latency>
<IterationLatency>163</IterationLatency>
</Loop5>
<Loop6>
<TripCount>4</TripCount>
<Latency>1036</Latency>
<IterationLatency>259</IterationLatency>
</Loop6>
</SummaryOfLoopLatency>
</PerformanceEstimates>

<AreaEstimates>
<Resources>
<FF>316</FF>
<LUT>2127</LUT>
<BRAM_18K>0</BRAM_18K>
<DSP48E>0</DSP48E>
<URAM>0</URAM>
</Resources>
<AvailableResources>
<BRAM_18K>730</BRAM_18K>
<DSP48E>740</DSP48E>
<FF>269200</FF>
<LUT>134600</LUT>
<URAM>0</URAM>
</AvailableResources>
</AreaEstimates>

<InterfaceSummary>
<RtlPorts>
<name>ap_clk</name>
<Object>pqcrystals_dilithium.2</Object>
<Type>return value</Type>
<Scope></Scope>
<IOProtocol>ap_ctrl_hs</IOProtocol>
<IOConfig></IOConfig>
<Dir>in</Dir>
<Bits>1</Bits>
<Attribute>control</Attribute>
</RtlPorts>
<RtlPorts>
<name>ap_rst</name>
<Object>pqcrystals_dilithium.2</Object>
<Type>return value</Type>
<Scope></Scope>
<IOProtocol>ap_ctrl_hs</IOProtocol>
<IOConfig></IOConfig>
<Dir>in</Dir>
<Bits>1</Bits>
<Attribute>control</Attribute>
</RtlPorts>
<RtlPorts>
<name>ap_start</name>
<Object>pqcrystals_dilithium.2</Object>
<Type>return value</Type>
<Scope></Scope>
<IOProtocol>ap_ctrl_hs</IOProtocol>
<IOConfig></IOConfig>
<Dir>in</Dir>
<Bits>1</Bits>
<Attribute>control</Attribute>
</RtlPorts>
<RtlPorts>
<name>ap_done</name>
<Object>pqcrystals_dilithium.2</Object>
<Type>return value</Type>
<Scope></Scope>
<IOProtocol>ap_ctrl_hs</IOProtocol>
<IOConfig></IOConfig>
<Dir>out</Dir>
<Bits>1</Bits>
<Attribute>control</Attribute>
</RtlPorts>
<RtlPorts>
<name>ap_idle</name>
<Object>pqcrystals_dilithium.2</Object>
<Type>return value</Type>
<Scope></Scope>
<IOProtocol>ap_ctrl_hs</IOProtocol>
<IOConfig></IOConfig>
<Dir>out</Dir>
<Bits>1</Bits>
<Attribute>control</Attribute>
</RtlPorts>
<RtlPorts>
<name>ap_ready</name>
<Object>pqcrystals_dilithium.2</Object>
<Type>return value</Type>
<Scope></Scope>
<IOProtocol>ap_ctrl_hs</IOProtocol>
<IOConfig></IOConfig>
<Dir>out</Dir>
<Bits>1</Bits>
<Attribute>control</Attribute>
</RtlPorts>
<RtlPorts>
<name>rho_address0</name>
<Object>rho</Object>
<Type>array</Type>
<Scope></Scope>
<IOProtocol>ap_memory</IOProtocol>
<IOConfig></IOConfig>
<Dir>out</Dir>
<Bits>8</Bits>
<Attribute>address</Attribute>
</RtlPorts>
<RtlPorts>
<name>rho_ce0</name>
<Object>rho</Object>
<Type>array</Type>
<Scope></Scope>
<IOProtocol>ap_memory</IOProtocol>
<IOConfig></IOConfig>
<Dir>out</Dir>
<Bits>1</Bits>
<Attribute>control</Attribute>
</RtlPorts>
<RtlPorts>
<name>rho_we0</name>
<Object>rho</Object>
<Type>array</Type>
<Scope></Scope>
<IOProtocol>ap_memory</IOProtocol>
<IOConfig></IOConfig>
<Dir>out</Dir>
<Bits>1</Bits>
<Attribute>control</Attribute>
</RtlPorts>
<RtlPorts>
<name>rho_d0</name>
<Object>rho</Object>
<Type>array</Type>
<Scope></Scope>
<IOProtocol>ap_memory</IOProtocol>
<IOConfig></IOConfig>
<Dir>out</Dir>
<Bits>8</Bits>
<Attribute>data</Attribute>
</RtlPorts>
<RtlPorts>
<name>t0_vec_coeffs_address0</name>
<Object>t0_vec_coeffs</Object>
<Type>array</Type>
<Scope></Scope>
<IOProtocol>ap_memory</IOProtocol>
<IOConfig></IOConfig>
<Dir>out</Dir>
<Bits>10</Bits>
<Attribute>address</Attribute>
</RtlPorts>
<RtlPorts>
<name>t0_vec_coeffs_ce0</name>
<Object>t0_vec_coeffs</Object>
<Type>array</Type>
<Scope></Scope>
<IOProtocol>ap_memory</IOProtocol>
<IOConfig></IOConfig>
<Dir>out</Dir>
<Bits>1</Bits>
<Attribute>control</Attribute>
</RtlPorts>
<RtlPorts>
<name>t0_vec_coeffs_we0</name>
<Object>t0_vec_coeffs</Object>
<Type>array</Type>
<Scope></Scope>
<IOProtocol>ap_memory</IOProtocol>
<IOConfig></IOConfig>
<Dir>out</Dir>
<Bits>1</Bits>
<Attribute>control</Attribute>
</RtlPorts>
<RtlPorts>
<name>t0_vec_coeffs_d0</name>
<Object>t0_vec_coeffs</Object>
<Type>array</Type>
<Scope></Scope>
<IOProtocol>ap_memory</IOProtocol>
<IOConfig></IOConfig>
<Dir>out</Dir>
<Bits>32</Bits>
<Attribute>data</Attribute>
</RtlPorts>
<RtlPorts>
<name>t0_vec_coeffs_address1</name>
<Object>t0_vec_coeffs</Object>
<Type>array</Type>
<Scope></Scope>
<IOProtocol>ap_memory</IOProtocol>
<IOConfig></IOConfig>
<Dir>out</Dir>
<Bits>10</Bits>
<Attribute>address</Attribute>
</RtlPorts>
<RtlPorts>
<name>t0_vec_coeffs_ce1</name>
<Object>t0_vec_coeffs</Object>
<Type>array</Type>
<Scope></Scope>
<IOProtocol>ap_memory</IOProtocol>
<IOConfig></IOConfig>
<Dir>out</Dir>
<Bits>1</Bits>
<Attribute>control</Attribute>
</RtlPorts>
<RtlPorts>
<name>t0_vec_coeffs_we1</name>
<Object>t0_vec_coeffs</Object>
<Type>array</Type>
<Scope></Scope>
<IOProtocol>ap_memory</IOProtocol>
<IOConfig></IOConfig>
<Dir>out</Dir>
<Bits>1</Bits>
<Attribute>control</Attribute>
</RtlPorts>
<RtlPorts>
<name>t0_vec_coeffs_d1</name>
<Object>t0_vec_coeffs</Object>
<Type>array</Type>
<Scope></Scope>
<IOProtocol>ap_memory</IOProtocol>
<IOConfig></IOConfig>
<Dir>out</Dir>
<Bits>32</Bits>
<Attribute>data</Attribute>
</RtlPorts>
<RtlPorts>
<name>s1_vec_coeffs_address0</name>
<Object>s1_vec_coeffs</Object>
<Type>array</Type>
<Scope></Scope>
<IOProtocol>ap_memory</IOProtocol>
<IOConfig></IOConfig>
<Dir>out</Dir>
<Bits>10</Bits>
<Attribute>address</Attribute>
</RtlPorts>
<RtlPorts>
<name>s1_vec_coeffs_ce0</name>
<Object>s1_vec_coeffs</Object>
<Type>array</Type>
<Scope></Scope>
<IOProtocol>ap_memory</IOProtocol>
<IOConfig></IOConfig>
<Dir>out</Dir>
<Bits>1</Bits>
<Attribute>control</Attribute>
</RtlPorts>
<RtlPorts>
<name>s1_vec_coeffs_we0</name>
<Object>s1_vec_coeffs</Object>
<Type>array</Type>
<Scope></Scope>
<IOProtocol>ap_memory</IOProtocol>
<IOConfig></IOConfig>
<Dir>out</Dir>
<Bits>1</Bits>
<Attribute>control</Attribute>
</RtlPorts>
<RtlPorts>
<name>s1_vec_coeffs_d0</name>
<Object>s1_vec_coeffs</Object>
<Type>array</Type>
<Scope></Scope>
<IOProtocol>ap_memory</IOProtocol>
<IOConfig></IOConfig>
<Dir>out</Dir>
<Bits>32</Bits>
<Attribute>data</Attribute>
</RtlPorts>
<RtlPorts>
<name>s1_vec_coeffs_address1</name>
<Object>s1_vec_coeffs</Object>
<Type>array</Type>
<Scope></Scope>
<IOProtocol>ap_memory</IOProtocol>
<IOConfig></IOConfig>
<Dir>out</Dir>
<Bits>10</Bits>
<Attribute>address</Attribute>
</RtlPorts>
<RtlPorts>
<name>s1_vec_coeffs_ce1</name>
<Object>s1_vec_coeffs</Object>
<Type>array</Type>
<Scope></Scope>
<IOProtocol>ap_memory</IOProtocol>
<IOConfig></IOConfig>
<Dir>out</Dir>
<Bits>1</Bits>
<Attribute>control</Attribute>
</RtlPorts>
<RtlPorts>
<name>s1_vec_coeffs_we1</name>
<Object>s1_vec_coeffs</Object>
<Type>array</Type>
<Scope></Scope>
<IOProtocol>ap_memory</IOProtocol>
<IOConfig></IOConfig>
<Dir>out</Dir>
<Bits>1</Bits>
<Attribute>control</Attribute>
</RtlPorts>
<RtlPorts>
<name>s1_vec_coeffs_d1</name>
<Object>s1_vec_coeffs</Object>
<Type>array</Type>
<Scope></Scope>
<IOProtocol>ap_memory</IOProtocol>
<IOConfig></IOConfig>
<Dir>out</Dir>
<Bits>32</Bits>
<Attribute>data</Attribute>
</RtlPorts>
<RtlPorts>
<name>s2_vec_coeffs_address0</name>
<Object>s2_vec_coeffs</Object>
<Type>array</Type>
<Scope></Scope>
<IOProtocol>ap_memory</IOProtocol>
<IOConfig></IOConfig>
<Dir>out</Dir>
<Bits>10</Bits>
<Attribute>address</Attribute>
</RtlPorts>
<RtlPorts>
<name>s2_vec_coeffs_ce0</name>
<Object>s2_vec_coeffs</Object>
<Type>array</Type>
<Scope></Scope>
<IOProtocol>ap_memory</IOProtocol>
<IOConfig></IOConfig>
<Dir>out</Dir>
<Bits>1</Bits>
<Attribute>control</Attribute>
</RtlPorts>
<RtlPorts>
<name>s2_vec_coeffs_we0</name>
<Object>s2_vec_coeffs</Object>
<Type>array</Type>
<Scope></Scope>
<IOProtocol>ap_memory</IOProtocol>
<IOConfig></IOConfig>
<Dir>out</Dir>
<Bits>1</Bits>
<Attribute>control</Attribute>
</RtlPorts>
<RtlPorts>
<name>s2_vec_coeffs_d0</name>
<Object>s2_vec_coeffs</Object>
<Type>array</Type>
<Scope></Scope>
<IOProtocol>ap_memory</IOProtocol>
<IOConfig></IOConfig>
<Dir>out</Dir>
<Bits>32</Bits>
<Attribute>data</Attribute>
</RtlPorts>
<RtlPorts>
<name>s2_vec_coeffs_address1</name>
<Object>s2_vec_coeffs</Object>
<Type>array</Type>
<Scope></Scope>
<IOProtocol>ap_memory</IOProtocol>
<IOConfig></IOConfig>
<Dir>out</Dir>
<Bits>10</Bits>
<Attribute>address</Attribute>
</RtlPorts>
<RtlPorts>
<name>s2_vec_coeffs_ce1</name>
<Object>s2_vec_coeffs</Object>
<Type>array</Type>
<Scope></Scope>
<IOProtocol>ap_memory</IOProtocol>
<IOConfig></IOConfig>
<Dir>out</Dir>
<Bits>1</Bits>
<Attribute>control</Attribute>
</RtlPorts>
<RtlPorts>
<name>s2_vec_coeffs_we1</name>
<Object>s2_vec_coeffs</Object>
<Type>array</Type>
<Scope></Scope>
<IOProtocol>ap_memory</IOProtocol>
<IOConfig></IOConfig>
<Dir>out</Dir>
<Bits>1</Bits>
<Attribute>control</Attribute>
</RtlPorts>
<RtlPorts>
<name>s2_vec_coeffs_d1</name>
<Object>s2_vec_coeffs</Object>
<Type>array</Type>
<Scope></Scope>
<IOProtocol>ap_memory</IOProtocol>
<IOConfig></IOConfig>
<Dir>out</Dir>
<Bits>32</Bits>
<Attribute>data</Attribute>
</RtlPorts>
<RtlPorts>
<name>sk_address0</name>
<Object>sk</Object>
<Type>array</Type>
<Scope></Scope>
<IOProtocol>ap_memory</IOProtocol>
<IOConfig></IOConfig>
<Dir>out</Dir>
<Bits>12</Bits>
<Attribute>address</Attribute>
</RtlPorts>
<RtlPorts>
<name>sk_ce0</name>
<Object>sk</Object>
<Type>array</Type>
<Scope></Scope>
<IOProtocol>ap_memory</IOProtocol>
<IOConfig></IOConfig>
<Dir>out</Dir>
<Bits>1</Bits>
<Attribute>control</Attribute>
</RtlPorts>
<RtlPorts>
<name>sk_q0</name>
<Object>sk</Object>
<Type>array</Type>
<Scope></Scope>
<IOProtocol>ap_memory</IOProtocol>
<IOConfig></IOConfig>
<Dir>in</Dir>
<Bits>8</Bits>
<Attribute>data</Attribute>
</RtlPorts>
<RtlPorts>
<name>sk_address1</name>
<Object>sk</Object>
<Type>array</Type>
<Scope></Scope>
<IOProtocol>ap_memory</IOProtocol>
<IOConfig></IOConfig>
<Dir>out</Dir>
<Bits>12</Bits>
<Attribute>address</Attribute>
</RtlPorts>
<RtlPorts>
<name>sk_ce1</name>
<Object>sk</Object>
<Type>array</Type>
<Scope></Scope>
<IOProtocol>ap_memory</IOProtocol>
<IOConfig></IOConfig>
<Dir>out</Dir>
<Bits>1</Bits>
<Attribute>control</Attribute>
</RtlPorts>
<RtlPorts>
<name>sk_q1</name>
<Object>sk</Object>
<Type>array</Type>
<Scope></Scope>
<IOProtocol>ap_memory</IOProtocol>
<IOConfig></IOConfig>
<Dir>in</Dir>
<Bits>8</Bits>
<Attribute>data</Attribute>
</RtlPorts>
</InterfaceSummary>

</profile>
