<stg><name>pqcrystals_dilithium.18</name>


<trans_list>

<trans id="93" from="1" to="2">
<condition id="-1">
<or_exp><and_exp></and_exp></or_exp>
</condition>
</trans>

<trans id="94" from="2" to="3">
<condition id="-1">
<or_exp><and_exp><literal name="icmp_ln54" val="0"/>
</and_exp></or_exp>
</condition>
</trans>

<trans id="95" from="3" to="4">
<condition id="-1">
<or_exp><and_exp><literal name="icmp_ln55" val="1"/>
</and_exp></or_exp>
</condition>
</trans>

<trans id="108" from="3" to="2">
<condition id="-1">
<or_exp><and_exp><literal name="icmp_ln55" val="0"/>
</and_exp></or_exp>
</condition>
</trans>

<trans id="97" from="4" to="5">
<condition id="-1">
<or_exp><and_exp></and_exp></or_exp>
</condition>
</trans>

<trans id="98" from="5" to="6">
<condition id="-1">
<or_exp><and_exp><literal name="icmp_ln57" val="1"/>
</and_exp></or_exp>
</condition>
</trans>

<trans id="107" from="5" to="3">
<condition id="-1">
<or_exp><and_exp><literal name="icmp_ln57" val="0"/>
</and_exp></or_exp>
</condition>
</trans>

<trans id="100" from="6" to="7">
<condition id="-1">
<or_exp><and_exp></and_exp></or_exp>
</condition>
</trans>

<trans id="101" from="7" to="8">
<condition id="-1">
<or_exp><and_exp></and_exp></or_exp>
</condition>
</trans>

<trans id="102" from="8" to="9">
<condition id="-1">
<or_exp><and_exp></and_exp></or_exp>
</condition>
</trans>

<trans id="103" from="9" to="10">
<condition id="-1">
<or_exp><and_exp></and_exp></or_exp>
</condition>
</trans>

<trans id="104" from="10" to="11">
<condition id="-1">
<or_exp><and_exp></and_exp></or_exp>
</condition>
</trans>

<trans id="105" from="11" to="12">
<condition id="-1">
<or_exp><and_exp></and_exp></or_exp>
</condition>
</trans>

<trans id="106" from="12" to="5">
<condition id="-1">
<or_exp><and_exp></and_exp></or_exp>
</condition>
</trans>
</trans_list>



<state_list>

<state id="1" st_id="1">

<operation id="13" st_id="1" stage="1" lat="1">
<core>NULL</core>
<MemPortIdVec></MemPortIdVec>
<condition id="-1">
<or_exp><and_exp></and_exp></or_exp>
</condition>

<Node id="4" bw="32" op_0_bw="32">
<![CDATA[
:0  %k_3 = alloca i32

]]></Node>
<StgValue><ssdm name="k_3"/></StgValue>
</operation>

<operation id="14" st_id="1" stage="1" lat="1">
<core>NULL</core>
<MemPortIdVec></MemPortIdVec>
<condition id="-1">
<or_exp><and_exp></and_exp></or_exp>
</condition>

<Node id="5" bw="0" op_0_bw="32" op_1_bw="32">
<![CDATA[
:1  store i32 0, i32* %k_3

]]></Node>
<StgValue><ssdm name="store_ln54"/></StgValue>
</operation>

<operation id="15" st_id="1" stage="1" lat="1">
<core>NULL</core>
<MemPortIdVec></MemPortIdVec>
<condition id="-1">
<or_exp><and_exp></and_exp></or_exp>
</condition>

<Node id="6" bw="0" op_0_bw="0">
<![CDATA[
:2  br label %1

]]></Node>
<StgValue><ssdm name="br_ln54"/></StgValue>
</operation>
</state>

<state id="2" st_id="2">

<operation id="16" st_id="2" stage="1" lat="1">
<core>NULL</core>
<MemPortIdVec></MemPortIdVec>
<condition id="-1">
<or_exp><and_exp></and_exp></or_exp>
</condition>

<Node id="8" bw="29" op_0_bw="29" op_1_bw="0" op_2_bw="29" op_3_bw="0">
<![CDATA[
:0  %len_0 = phi i29 [ 128, %0 ], [ %zext_ln54_3, %pqcrystals_dilithium2_ref_ntt_label7_end ]

]]></Node>
<StgValue><ssdm name="len_0"/></StgValue>
</operation>

<operation id="17" st_id="2" stage="1" lat="1">
<core>Cmp</core>
<MemPortIdVec></MemPortIdVec>
<condition id="-1">
<or_exp><and_exp></and_exp></or_exp>
</condition>

<Node id="9" bw="1" op_0_bw="29" op_1_bw="29">
<![CDATA[
:1  %icmp_ln54 = icmp eq i29 %len_0, 0

]]></Node>
<StgValue><ssdm name="icmp_ln54"/></StgValue>
</operation>

<operation id="18" st_id="2" stage="1" lat="1">
<core>NULL</core>
<MemPortIdVec></MemPortIdVec>
<condition id="-1">
<or_exp><and_exp></and_exp></or_exp>
</condition>

<Node id="10" bw="0" op_0_bw="0" op_1_bw="64" op_2_bw="64" op_3_bw="64">
<![CDATA[
:2  call void (...)* @_ssdm_op_SpecLoopTripCount(i64 8, i64 8, i64 8)

]]></Node>
<StgValue><ssdm name="speclooptripcount_ln0"/></StgValue>
</operation>

<operation id="19" st_id="2" stage="1" lat="1">
<core>NULL</core>
<MemPortIdVec></MemPortIdVec>
<condition id="-1">
<or_exp><and_exp></and_exp></or_exp>
</condition>

<Node id="11" bw="0" op_0_bw="1" op_1_bw="0" op_2_bw="0">
<![CDATA[
:3  br i1 %icmp_ln54, label %4, label %pqcrystals_dilithium2_ref_ntt_label7_begin

]]></Node>
<StgValue><ssdm name="br_ln54"/></StgValue>
</operation>

<operation id="20" st_id="2" stage="1" lat="1">
<core>NULL</core>
<MemPortIdVec></MemPortIdVec>
<condition id="-1">
<or_exp><and_exp><literal name="icmp_ln54" val="0"/>
</and_exp></or_exp>
</condition>

<Node id="13" bw="32" op_0_bw="29">
<![CDATA[
pqcrystals_dilithium2_ref_ntt_label7_begin:0  %zext_ln54 = zext i29 %len_0 to i32

]]></Node>
<StgValue><ssdm name="zext_ln54"/></StgValue>
</operation>

<operation id="21" st_id="2" stage="1" lat="1">
<core>NULL</core>
<MemPortIdVec></MemPortIdVec>
<condition id="-1">
<or_exp><and_exp><literal name="icmp_ln54" val="0"/>
</and_exp></or_exp>
</condition>

<Node id="14" bw="31" op_0_bw="29">
<![CDATA[
pqcrystals_dilithium2_ref_ntt_label7_begin:1  %zext_ln54_2 = zext i29 %len_0 to i31

]]></Node>
<StgValue><ssdm name="zext_ln54_2"/></StgValue>
</operation>

<operation id="22" st_id="2" stage="1" lat="1">
<core>NULL</core>
<MemPortIdVec></MemPortIdVec>
<condition id="-1">
<or_exp><and_exp><literal name="icmp_ln54" val="0"/>
</and_exp></or_exp>
</condition>

<Node id="15" bw="0" op_0_bw="0" op_1_bw="0">
<![CDATA[
pqcrystals_dilithium2_ref_ntt_label7_begin:2  call void (...)* @_ssdm_op_SpecLoopName([37 x i8]* @p_str13) nounwind

]]></Node>
<StgValue><ssdm name="specloopname_ln54"/></StgValue>
</operation>

<operation id="23" st_id="2" stage="1" lat="1">
<core>NULL</core>
<MemPortIdVec></MemPortIdVec>
<condition id="-1">
<or_exp><and_exp><literal name="icmp_ln54" val="0"/>
</and_exp></or_exp>
</condition>

<Node id="16" bw="32" op_0_bw="32" op_1_bw="0">
<![CDATA[
pqcrystals_dilithium2_ref_ntt_label7_begin:3  %tmp = call i32 (...)* @_ssdm_op_SpecRegionBegin([37 x i8]* @p_str13)

]]></Node>
<StgValue><ssdm name="tmp"/></StgValue>
</operation>

<operation id="24" st_id="2" stage="1" lat="1">
<core>NULL</core>
<MemPortIdVec></MemPortIdVec>
<condition id="-1">
<or_exp><and_exp><literal name="icmp_ln54" val="0"/>
</and_exp></or_exp>
</condition>

<Node id="17" bw="0" op_0_bw="0">
<![CDATA[
pqcrystals_dilithium2_ref_ntt_label7_begin:4  br label %2

]]></Node>
<StgValue><ssdm name="br_ln55"/></StgValue>
</operation>

<operation id="25" st_id="2" stage="1" lat="1">
<core>NULL</core>
<MemPortIdVec></MemPortIdVec>
<condition id="-1">
<or_exp><and_exp><literal name="icmp_ln54" val="1"/>
</and_exp></or_exp>
</condition>

<Node id="88" bw="0">
<![CDATA[
:0  ret void

]]></Node>
<StgValue><ssdm name="ret_ln64"/></StgValue>
</operation>
</state>

<state id="3" st_id="3">

<operation id="26" st_id="3" stage="1" lat="1">
<core>NULL</core>
<MemPortIdVec></MemPortIdVec>
<condition id="-1">
<or_exp><and_exp></and_exp></or_exp>
</condition>

<Node id="19" bw="31" op_0_bw="31" op_1_bw="0" op_2_bw="31" op_3_bw="0">
<![CDATA[
:0  %j = phi i31 [ 0, %pqcrystals_dilithium2_ref_ntt_label7_begin ], [ %add_ln55, %pqcrystals_dilithium2_ref_ntt_label8_end ]

]]></Node>
<StgValue><ssdm name="j"/></StgValue>
</operation>

<operation id="27" st_id="3" stage="1" lat="1">
<core>NULL</core>
<MemPortIdVec></MemPortIdVec>
<condition id="-1">
<or_exp><and_exp></and_exp></or_exp>
</condition>

<Node id="20" bw="32" op_0_bw="31">
<![CDATA[
:1  %zext_ln55 = zext i31 %j to i32

]]></Node>
<StgValue><ssdm name="zext_ln55"/></StgValue>
</operation>

<operation id="28" st_id="3" stage="1" lat="1">
<core>NULL</core>
<MemPortIdVec></MemPortIdVec>
<condition id="-1">
<or_exp><and_exp></and_exp></or_exp>
</condition>

<Node id="21" bw="23" op_0_bw="23" op_1_bw="31" op_2_bw="32" op_3_bw="32">
<![CDATA[
:2  %tmp_8 = call i23 @_ssdm_op_PartSelect.i23.i31.i32.i32(i31 %j, i32 8, i32 30)

]]></Node>
<StgValue><ssdm name="tmp_8"/></StgValue>
</operation>

<operation id="29" st_id="3" stage="1" lat="1">
<core>Cmp</core>
<MemPortIdVec></MemPortIdVec>
<condition id="-1">
<or_exp><and_exp></and_exp></or_exp>
</condition>

<Node id="22" bw="1" op_0_bw="23" op_1_bw="23">
<![CDATA[
:3  %icmp_ln55 = icmp eq i23 %tmp_8, 0

]]></Node>
<StgValue><ssdm name="icmp_ln55"/></StgValue>
</operation>

<operation id="30" st_id="3" stage="1" lat="1">
<core>NULL</core>
<MemPortIdVec></MemPortIdVec>
<condition id="-1">
<or_exp><and_exp></and_exp></or_exp>
</condition>

<Node id="23" bw="0" op_0_bw="1" op_1_bw="0" op_2_bw="0">
<![CDATA[
:4  br i1 %icmp_ln55, label %pqcrystals_dilithium2_ref_ntt_label8_begin, label %pqcrystals_dilithium2_ref_ntt_label7_end

]]></Node>
<StgValue><ssdm name="br_ln55"/></StgValue>
</operation>

<operation id="31" st_id="3" stage="1" lat="1">
<core>NULL</core>
<MemPortIdVec></MemPortIdVec>
<condition id="-1">
<or_exp><and_exp><literal name="icmp_ln55" val="1"/>
</and_exp></or_exp>
</condition>

<Node id="25" bw="32" op_0_bw="32" op_1_bw="0">
<![CDATA[
pqcrystals_dilithium2_ref_ntt_label8_begin:0  %k_3_load = load i32* %k_3

]]></Node>
<StgValue><ssdm name="k_3_load"/></StgValue>
</operation>

<operation id="32" st_id="3" stage="1" lat="1">
<core>AddSub</core>
<MemPortIdVec></MemPortIdVec>
<condition id="-1">
<or_exp><and_exp><literal name="icmp_ln55" val="1"/>
</and_exp></or_exp>
</condition>

<Node id="30" bw="32" op_0_bw="32" op_1_bw="32">
<![CDATA[
pqcrystals_dilithium2_ref_ntt_label8_begin:5  %k = add i32 1, %k_3_load

]]></Node>
<StgValue><ssdm name="k"/></StgValue>
</operation>

<operation id="33" st_id="3" stage="1" lat="1">
<core>NULL</core>
<MemPortIdVec></MemPortIdVec>
<condition id="-1">
<or_exp><and_exp><literal name="icmp_ln55" val="1"/>
</and_exp></or_exp>
</condition>

<Node id="31" bw="64" op_0_bw="32">
<![CDATA[
pqcrystals_dilithium2_ref_ntt_label8_begin:6  %zext_ln56 = zext i32 %k to i64

]]></Node>
<StgValue><ssdm name="zext_ln56"/></StgValue>
</operation>

<operation id="34" st_id="3" stage="1" lat="1">
<core>NULL</core>
<MemPortIdVec></MemPortIdVec>
<condition id="-1">
<or_exp><and_exp><literal name="icmp_ln55" val="1"/>
</and_exp></or_exp>
</condition>

<Node id="32" bw="8" op_0_bw="23" op_1_bw="64" op_2_bw="64">
<![CDATA[
pqcrystals_dilithium2_ref_ntt_label8_begin:7  %zetas_addr = getelementptr [256 x i23]* @zetas, i64 0, i64 %zext_ln56

]]></Node>
<StgValue><ssdm name="zetas_addr"/></StgValue>
</operation>

<operation id="35" st_id="3" stage="2" lat="2">
<core>ROM_nP</core>
<MemPortIdVec>0 </MemPortIdVec>
<condition id="-1">
<or_exp><and_exp><literal name="icmp_ln55" val="1"/>
</and_exp></or_exp>
</condition>

<Node id="33" bw="23" op_0_bw="8">
<![CDATA[
pqcrystals_dilithium2_ref_ntt_label8_begin:8  %zeta = load i23* %zetas_addr, align 4

]]></Node>
<StgValue><ssdm name="zeta"/></StgValue>
</operation>

<operation id="36" st_id="3" stage="1" lat="1">
<core>NULL</core>
<MemPortIdVec></MemPortIdVec>
<condition id="-1">
<or_exp><and_exp><literal name="icmp_ln55" val="0"/>
</and_exp></or_exp>
</condition>

<Node id="83" bw="32" op_0_bw="32" op_1_bw="0" op_2_bw="32">
<![CDATA[
pqcrystals_dilithium2_ref_ntt_label7_end:0  %empty_33 = call i32 (...)* @_ssdm_op_SpecRegionEnd([37 x i8]* @p_str13, i32 %tmp)

]]></Node>
<StgValue><ssdm name="empty_33"/></StgValue>
</operation>

<operation id="37" st_id="3" stage="1" lat="1">
<core>NULL</core>
<MemPortIdVec></MemPortIdVec>
<condition id="-1">
<or_exp><and_exp><literal name="icmp_ln55" val="0"/>
</and_exp></or_exp>
</condition>

<Node id="84" bw="28" op_0_bw="28" op_1_bw="29" op_2_bw="32" op_3_bw="32">
<![CDATA[
pqcrystals_dilithium2_ref_ntt_label7_end:1  %tmp_9 = call i28 @_ssdm_op_PartSelect.i28.i29.i32.i32(i29 %len_0, i32 1, i32 28)

]]></Node>
<StgValue><ssdm name="tmp_9"/></StgValue>
</operation>

<operation id="38" st_id="3" stage="1" lat="1">
<core>NULL</core>
<MemPortIdVec></MemPortIdVec>
<condition id="-1">
<or_exp><and_exp><literal name="icmp_ln55" val="0"/>
</and_exp></or_exp>
</condition>

<Node id="85" bw="29" op_0_bw="28">
<![CDATA[
pqcrystals_dilithium2_ref_ntt_label7_end:2  %zext_ln54_3 = zext i28 %tmp_9 to i29

]]></Node>
<StgValue><ssdm name="zext_ln54_3"/></StgValue>
</operation>

<operation id="39" st_id="3" stage="1" lat="1">
<core>NULL</core>
<MemPortIdVec></MemPortIdVec>
<condition id="-1">
<or_exp><and_exp><literal name="icmp_ln55" val="0"/>
</and_exp></or_exp>
</condition>

<Node id="86" bw="0" op_0_bw="0">
<![CDATA[
pqcrystals_dilithium2_ref_ntt_label7_end:3  br label %1

]]></Node>
<StgValue><ssdm name="br_ln54"/></StgValue>
</operation>
</state>

<state id="4" st_id="4">

<operation id="40" st_id="4" stage="1" lat="1">
<core>NULL</core>
<MemPortIdVec></MemPortIdVec>
<condition id="-1">
<or_exp><and_exp></and_exp></or_exp>
</condition>

<Node id="26" bw="0" op_0_bw="0" op_1_bw="0">
<![CDATA[
pqcrystals_dilithium2_ref_ntt_label8_begin:1  call void (...)* @_ssdm_op_SpecLoopName([37 x i8]* @p_str215) nounwind

]]></Node>
<StgValue><ssdm name="specloopname_ln55"/></StgValue>
</operation>

<operation id="41" st_id="4" stage="1" lat="1">
<core>NULL</core>
<MemPortIdVec></MemPortIdVec>
<condition id="-1">
<or_exp><and_exp></and_exp></or_exp>
</condition>

<Node id="27" bw="32" op_0_bw="32" op_1_bw="0">
<![CDATA[
pqcrystals_dilithium2_ref_ntt_label8_begin:2  %tmp_s = call i32 (...)* @_ssdm_op_SpecRegionBegin([37 x i8]* @p_str215)

]]></Node>
<StgValue><ssdm name="tmp_s"/></StgValue>
</operation>

<operation id="42" st_id="4" stage="1" lat="1">
<core>NULL</core>
<MemPortIdVec></MemPortIdVec>
<condition id="-1">
<or_exp><and_exp></and_exp></or_exp>
</condition>

<Node id="28" bw="0" op_0_bw="0" op_1_bw="32" op_2_bw="32" op_3_bw="32" op_4_bw="0">
<![CDATA[
pqcrystals_dilithium2_ref_ntt_label8_begin:3  call void (...)* @_ssdm_op_SpecLoopTripCount(i32 0, i32 256, i32 128, [1 x i8]* @p_str114) nounwind

]]></Node>
<StgValue><ssdm name="speclooptripcount_ln56"/></StgValue>
</operation>

<operation id="43" st_id="4" stage="1" lat="1">
<core>NULL</core>
<MemPortIdVec></MemPortIdVec>
<condition id="-1">
<or_exp><and_exp></and_exp></or_exp>
</condition>

<Node id="29" bw="0" op_0_bw="0" op_1_bw="32" op_2_bw="32" op_3_bw="32" op_4_bw="32" op_5_bw="0">
<![CDATA[
pqcrystals_dilithium2_ref_ntt_label8_begin:4  call void (...)* @_ssdm_op_SpecPipeline(i32 -1, i32 1, i32 1, i32 0, [1 x i8]* @p_str114) nounwind

]]></Node>
<StgValue><ssdm name="specpipeline_ln56"/></StgValue>
</operation>

<operation id="44" st_id="4" stage="1" lat="2">
<core>ROM_nP</core>
<MemPortIdVec>0 </MemPortIdVec>
<condition id="-1">
<or_exp><and_exp></and_exp></or_exp>
</condition>

<Node id="33" bw="23" op_0_bw="8">
<![CDATA[
pqcrystals_dilithium2_ref_ntt_label8_begin:8  %zeta = load i23* %zetas_addr, align 4

]]></Node>
<StgValue><ssdm name="zeta"/></StgValue>
</operation>

<operation id="45" st_id="4" stage="1" lat="1">
<core>AddSub</core>
<MemPortIdVec></MemPortIdVec>
<condition id="-1">
<or_exp><and_exp></and_exp></or_exp>
</condition>

<Node id="34" bw="31" op_0_bw="31" op_1_bw="31">
<![CDATA[
pqcrystals_dilithium2_ref_ntt_label8_begin:9  %add_ln57 = add i31 %zext_ln54_2, %j

]]></Node>
<StgValue><ssdm name="add_ln57"/></StgValue>
</operation>

<operation id="46" st_id="4" stage="1" lat="1">
<core>NULL</core>
<MemPortIdVec></MemPortIdVec>
<condition id="-1">
<or_exp><and_exp></and_exp></or_exp>
</condition>

<Node id="35" bw="32" op_0_bw="31">
<![CDATA[
pqcrystals_dilithium2_ref_ntt_label8_begin:10  %zext_ln57 = zext i31 %add_ln57 to i32

]]></Node>
<StgValue><ssdm name="zext_ln57"/></StgValue>
</operation>

<operation id="47" st_id="4" stage="1" lat="1">
<core>Cmp</core>
<MemPortIdVec></MemPortIdVec>
<condition id="-1">
<or_exp><and_exp></and_exp></or_exp>
</condition>

<Node id="36" bw="1" op_0_bw="31" op_1_bw="31">
<![CDATA[
pqcrystals_dilithium2_ref_ntt_label8_begin:11  %empty = icmp ugt i31 %j, %add_ln57

]]></Node>
<StgValue><ssdm name="empty"/></StgValue>
</operation>

<operation id="48" st_id="4" stage="1" lat="1">
<core>NULL</core>
<MemPortIdVec></MemPortIdVec>
<condition id="-1">
<or_exp><and_exp></and_exp></or_exp>
</condition>

<Node id="37" bw="30" op_0_bw="31">
<![CDATA[
pqcrystals_dilithium2_ref_ntt_label8_begin:12  %trunc_ln55 = trunc i31 %j to i30

]]></Node>
<StgValue><ssdm name="trunc_ln55"/></StgValue>
</operation>

<operation id="49" st_id="4" stage="1" lat="1">
<core>NULL</core>
<MemPortIdVec></MemPortIdVec>
<condition id="-1">
<or_exp><and_exp></and_exp></or_exp>
</condition>

<Node id="38" bw="30" op_0_bw="31">
<![CDATA[
pqcrystals_dilithium2_ref_ntt_label8_begin:13  %trunc_ln55_2 = trunc i31 %add_ln57 to i30

]]></Node>
<StgValue><ssdm name="trunc_ln55_2"/></StgValue>
</operation>

<operation id="50" st_id="4" stage="1" lat="1">
<core>Sel</core>
<MemPortIdVec></MemPortIdVec>
<condition id="-1">
<or_exp><and_exp></and_exp></or_exp>
</condition>

<Node id="39" bw="30" op_0_bw="1" op_1_bw="30" op_2_bw="30">
<![CDATA[
pqcrystals_dilithium2_ref_ntt_label8_begin:14  %start = select i1 %empty, i30 %trunc_ln55, i30 %trunc_ln55_2

]]></Node>
<StgValue><ssdm name="start"/></StgValue>
</operation>

<operation id="51" st_id="4" stage="1" lat="1">
<core>NULL</core>
<MemPortIdVec></MemPortIdVec>
<condition id="-1">
<or_exp><and_exp></and_exp></or_exp>
</condition>

<Node id="40" bw="31" op_0_bw="30">
<![CDATA[
pqcrystals_dilithium2_ref_ntt_label8_begin:15  %zext_ln55_2 = zext i30 %start to i31

]]></Node>
<StgValue><ssdm name="zext_ln55_2"/></StgValue>
</operation>

<operation id="52" st_id="4" stage="1" lat="1">
<core>NULL</core>
<MemPortIdVec></MemPortIdVec>
<condition id="-1">
<or_exp><and_exp></and_exp></or_exp>
</condition>

<Node id="41" bw="54" op_0_bw="23">
<![CDATA[
pqcrystals_dilithium2_ref_ntt_label8_begin:16  %sext_ln57 = sext i23 %zeta to i54

]]></Node>
<StgValue><ssdm name="sext_ln57"/></StgValue>
</operation>

<operation id="53" st_id="4" stage="1" lat="1">
<core>NULL</core>
<MemPortIdVec></MemPortIdVec>
<condition id="-1">
<or_exp><and_exp></and_exp></or_exp>
</condition>

<Node id="42" bw="0" op_0_bw="0">
<![CDATA[
pqcrystals_dilithium2_ref_ntt_label8_begin:17  br label %3

]]></Node>
<StgValue><ssdm name="br_ln57"/></StgValue>
</operation>
</state>

<state id="5" st_id="5">

<operation id="54" st_id="5" stage="1" lat="1">
<core>NULL</core>
<MemPortIdVec></MemPortIdVec>
<condition id="-1">
<or_exp><and_exp></and_exp></or_exp>
</condition>

<Node id="44" bw="32" op_0_bw="32" op_1_bw="0" op_2_bw="32" op_3_bw="0">
<![CDATA[
:0  %j_0 = phi i32 [ %zext_ln55, %pqcrystals_dilithium2_ref_ntt_label8_begin ], [ %j_5, %pqcrystals_dilithium2_ref_ntt_label9 ]

]]></Node>
<StgValue><ssdm name="j_0"/></StgValue>
</operation>

<operation id="55" st_id="5" stage="1" lat="1">
<core>Cmp</core>
<MemPortIdVec></MemPortIdVec>
<condition id="-1">
<or_exp><and_exp></and_exp></or_exp>
</condition>

<Node id="45" bw="1" op_0_bw="32" op_1_bw="32">
<![CDATA[
:1  %icmp_ln57 = icmp ult i32 %j_0, %zext_ln57

]]></Node>
<StgValue><ssdm name="icmp_ln57"/></StgValue>
</operation>

<operation id="56" st_id="5" stage="1" lat="1">
<core>NULL</core>
<MemPortIdVec></MemPortIdVec>
<condition id="-1">
<or_exp><and_exp></and_exp></or_exp>
</condition>

<Node id="46" bw="0" op_0_bw="1" op_1_bw="0" op_2_bw="0">
<![CDATA[
:2  br i1 %icmp_ln57, label %pqcrystals_dilithium2_ref_ntt_label9, label %pqcrystals_dilithium2_ref_ntt_label8_end

]]></Node>
<StgValue><ssdm name="br_ln57"/></StgValue>
</operation>

<operation id="57" st_id="5" stage="1" lat="1">
<core>AddSub</core>
<MemPortIdVec></MemPortIdVec>
<condition id="-1">
<or_exp><and_exp><literal name="icmp_ln57" val="1"/>
</and_exp></or_exp>
</condition>

<Node id="51" bw="32" op_0_bw="32" op_1_bw="32">
<![CDATA[
pqcrystals_dilithium2_ref_ntt_label9:3  %add_ln58 = add i32 %zext_ln54, %j_0

]]></Node>
<StgValue><ssdm name="add_ln58"/></StgValue>
</operation>

<operation id="58" st_id="5" stage="1" lat="1">
<core>NULL</core>
<MemPortIdVec></MemPortIdVec>
<condition id="-1">
<or_exp><and_exp><literal name="icmp_ln57" val="1"/>
</and_exp></or_exp>
</condition>

<Node id="52" bw="64" op_0_bw="32">
<![CDATA[
pqcrystals_dilithium2_ref_ntt_label9:4  %zext_ln58 = zext i32 %add_ln58 to i64

]]></Node>
<StgValue><ssdm name="zext_ln58"/></StgValue>
</operation>

<operation id="59" st_id="5" stage="1" lat="1">
<core>NULL</core>
<MemPortIdVec></MemPortIdVec>
<condition id="-1">
<or_exp><and_exp><literal name="icmp_ln57" val="1"/>
</and_exp></or_exp>
</condition>

<Node id="53" bw="8" op_0_bw="32" op_1_bw="64" op_2_bw="64">
<![CDATA[
pqcrystals_dilithium2_ref_ntt_label9:5  %a_addr = getelementptr [256 x i32]* %a, i64 0, i64 %zext_ln58

]]></Node>
<StgValue><ssdm name="a_addr"/></StgValue>
</operation>

<operation id="60" st_id="5" stage="2" lat="2">
<core>RAM</core>
<MemPortIdVec>0 </MemPortIdVec>
<condition id="-1">
<or_exp><and_exp><literal name="icmp_ln57" val="1"/>
</and_exp></or_exp>
</condition>

<Node id="54" bw="32" op_0_bw="8">
<![CDATA[
pqcrystals_dilithium2_ref_ntt_label9:6  %a_load = load i32* %a_addr, align 4

]]></Node>
<StgValue><ssdm name="a_load"/></StgValue>
</operation>

<operation id="61" st_id="5" stage="1" lat="1">
<core>NULL</core>
<MemPortIdVec></MemPortIdVec>
<condition id="-1">
<or_exp><and_exp><literal name="icmp_ln57" val="1"/>
</and_exp></or_exp>
</condition>

<Node id="66" bw="64" op_0_bw="32">
<![CDATA[
pqcrystals_dilithium2_ref_ntt_label9:18  %zext_ln59 = zext i32 %j_0 to i64

]]></Node>
<StgValue><ssdm name="zext_ln59"/></StgValue>
</operation>

<operation id="62" st_id="5" stage="1" lat="1">
<core>NULL</core>
<MemPortIdVec></MemPortIdVec>
<condition id="-1">
<or_exp><and_exp><literal name="icmp_ln57" val="1"/>
</and_exp></or_exp>
</condition>

<Node id="67" bw="8" op_0_bw="32" op_1_bw="64" op_2_bw="64">
<![CDATA[
pqcrystals_dilithium2_ref_ntt_label9:19  %a_addr_3 = getelementptr [256 x i32]* %a, i64 0, i64 %zext_ln59

]]></Node>
<StgValue><ssdm name="a_addr_3"/></StgValue>
</operation>

<operation id="63" st_id="5" stage="1" lat="1">
<core>AddSub</core>
<MemPortIdVec></MemPortIdVec>
<condition id="-1">
<or_exp><and_exp><literal name="icmp_ln57" val="1"/>
</and_exp></or_exp>
</condition>

<Node id="75" bw="32" op_0_bw="32" op_1_bw="32">
<![CDATA[
pqcrystals_dilithium2_ref_ntt_label9:27  %j_5 = add i32 1, %j_0

]]></Node>
<StgValue><ssdm name="j_5"/></StgValue>
</operation>

<operation id="64" st_id="5" stage="1" lat="1">
<core>NULL</core>
<MemPortIdVec></MemPortIdVec>
<condition id="-1">
<or_exp><and_exp><literal name="icmp_ln57" val="0"/>
</and_exp></or_exp>
</condition>

<Node id="78" bw="32" op_0_bw="32" op_1_bw="0" op_2_bw="32">
<![CDATA[
pqcrystals_dilithium2_ref_ntt_label8_end:0  %empty_32 = call i32 (...)* @_ssdm_op_SpecRegionEnd([37 x i8]* @p_str215, i32 %tmp_s)

]]></Node>
<StgValue><ssdm name="empty_32"/></StgValue>
</operation>

<operation id="65" st_id="5" stage="1" lat="1">
<core>AddSub</core>
<MemPortIdVec></MemPortIdVec>
<condition id="-1">
<or_exp><and_exp><literal name="icmp_ln57" val="0"/>
</and_exp></or_exp>
</condition>

<Node id="79" bw="31" op_0_bw="31" op_1_bw="31">
<![CDATA[
pqcrystals_dilithium2_ref_ntt_label8_end:1  %add_ln55 = add i31 %zext_ln54_2, %zext_ln55_2

]]></Node>
<StgValue><ssdm name="add_ln55"/></StgValue>
</operation>

<operation id="66" st_id="5" stage="1" lat="1">
<core>NULL</core>
<MemPortIdVec></MemPortIdVec>
<condition id="-1">
<or_exp><and_exp><literal name="icmp_ln57" val="0"/>
</and_exp></or_exp>
</condition>

<Node id="80" bw="0" op_0_bw="32" op_1_bw="32" op_2_bw="0" op_3_bw="32">
<![CDATA[
pqcrystals_dilithium2_ref_ntt_label8_end:2  store i32 %k, i32* %k_3

]]></Node>
<StgValue><ssdm name="store_ln55"/></StgValue>
</operation>

<operation id="67" st_id="5" stage="1" lat="1">
<core>NULL</core>
<MemPortIdVec></MemPortIdVec>
<condition id="-1">
<or_exp><and_exp><literal name="icmp_ln57" val="0"/>
</and_exp></or_exp>
</condition>

<Node id="81" bw="0" op_0_bw="0">
<![CDATA[
pqcrystals_dilithium2_ref_ntt_label8_end:3  br label %2

]]></Node>
<StgValue><ssdm name="br_ln55"/></StgValue>
</operation>
</state>

<state id="6" st_id="6">

<operation id="68" st_id="6" stage="1" lat="2">
<core>RAM</core>
<MemPortIdVec>0 </MemPortIdVec>
<condition id="-1">
<or_exp><and_exp></and_exp></or_exp>
</condition>

<Node id="54" bw="32" op_0_bw="8">
<![CDATA[
pqcrystals_dilithium2_ref_ntt_label9:6  %a_load = load i32* %a_addr, align 4

]]></Node>
<StgValue><ssdm name="a_load"/></StgValue>
</operation>
</state>

<state id="7" st_id="7">

<operation id="69" st_id="7" stage="1" lat="1">
<core>NULL</core>
<MemPortIdVec></MemPortIdVec>
<condition id="-1">
<or_exp><and_exp></and_exp></or_exp>
</condition>

<Node id="55" bw="54" op_0_bw="32">
<![CDATA[
pqcrystals_dilithium2_ref_ntt_label9:7  %sext_ln58 = sext i32 %a_load to i54

]]></Node>
<StgValue><ssdm name="sext_ln58"/></StgValue>
</operation>

<operation id="70" st_id="7" stage="1" lat="1">
<core>Mul</core>
<MemPortIdVec></MemPortIdVec>
<condition id="-1">
<or_exp><and_exp></and_exp></or_exp>
</condition>

<Node id="56" bw="54" op_0_bw="54" op_1_bw="54">
<![CDATA[
pqcrystals_dilithium2_ref_ntt_label9:8  %mul_ln58 = mul i54 %sext_ln57, %sext_ln58

]]></Node>
<StgValue><ssdm name="mul_ln58"/></StgValue>
</operation>

<operation id="71" st_id="7" stage="1" lat="1">
<core>NULL</core>
<MemPortIdVec></MemPortIdVec>
<condition id="-1">
<or_exp><and_exp></and_exp></or_exp>
</condition>

<Node id="58" bw="32" op_0_bw="54">
<![CDATA[
pqcrystals_dilithium2_ref_ntt_label9:10  %trunc_ln18 = trunc i54 %mul_ln58 to i32

]]></Node>
<StgValue><ssdm name="trunc_ln18"/></StgValue>
</operation>
</state>

<state id="8" st_id="8">

<operation id="72" st_id="8" stage="1" lat="1">
<core>Mul</core>
<MemPortIdVec></MemPortIdVec>
<condition id="-1">
<or_exp><and_exp></and_exp></or_exp>
</condition>

<Node id="59" bw="32" op_0_bw="32" op_1_bw="32">
<![CDATA[
pqcrystals_dilithium2_ref_ntt_label9:11  %t = mul nsw i32 58728449, %trunc_ln18

]]></Node>
<StgValue><ssdm name="t"/></StgValue>
</operation>
</state>

<state id="9" st_id="9">

<operation id="73" st_id="9" stage="1" lat="1">
<core>NULL</core>
<MemPortIdVec></MemPortIdVec>
<condition id="-1">
<or_exp><and_exp></and_exp></or_exp>
</condition>

<Node id="60" bw="55" op_0_bw="32">
<![CDATA[
pqcrystals_dilithium2_ref_ntt_label9:12  %sext_ln19 = sext i32 %t to i55

]]></Node>
<StgValue><ssdm name="sext_ln19"/></StgValue>
</operation>

<operation id="74" st_id="9" stage="1" lat="1">
<core>Mul</core>
<MemPortIdVec></MemPortIdVec>
<condition id="-1">
<or_exp><and_exp></and_exp></or_exp>
</condition>

<Node id="61" bw="55" op_0_bw="55" op_1_bw="55">
<![CDATA[
pqcrystals_dilithium2_ref_ntt_label9:13  %mul_ln19 = mul i55 -8380417, %sext_ln19

]]></Node>
<StgValue><ssdm name="mul_ln19"/></StgValue>
</operation>

<operation id="75" st_id="9" stage="2" lat="2">
<core>RAM</core>
<MemPortIdVec>0 </MemPortIdVec>
<condition id="-1">
<or_exp><and_exp></and_exp></or_exp>
</condition>

<Node id="68" bw="32" op_0_bw="8">
<![CDATA[
pqcrystals_dilithium2_ref_ntt_label9:20  %a_load_6 = load i32* %a_addr_3, align 4

]]></Node>
<StgValue><ssdm name="a_load_6"/></StgValue>
</operation>
</state>

<state id="10" st_id="10">

<operation id="76" st_id="10" stage="1" lat="1">
<core>NULL</core>
<MemPortIdVec></MemPortIdVec>
<condition id="-1">
<or_exp><and_exp></and_exp></or_exp>
</condition>

<Node id="57" bw="56" op_0_bw="54">
<![CDATA[
pqcrystals_dilithium2_ref_ntt_label9:9  %sext_ln58_1 = sext i54 %mul_ln58 to i56

]]></Node>
<StgValue><ssdm name="sext_ln58_1"/></StgValue>
</operation>

<operation id="77" st_id="10" stage="1" lat="1">
<core>NULL</core>
<MemPortIdVec></MemPortIdVec>
<condition id="-1">
<or_exp><and_exp></and_exp></or_exp>
</condition>

<Node id="62" bw="56" op_0_bw="55">
<![CDATA[
pqcrystals_dilithium2_ref_ntt_label9:14  %sext_ln19_4 = sext i55 %mul_ln19 to i56

]]></Node>
<StgValue><ssdm name="sext_ln19_4"/></StgValue>
</operation>

<operation id="78" st_id="10" stage="1" lat="1">
<core>AddSub</core>
<MemPortIdVec></MemPortIdVec>
<condition id="-1">
<or_exp><and_exp></and_exp></or_exp>
</condition>

<Node id="63" bw="56" op_0_bw="56" op_1_bw="56">
<![CDATA[
pqcrystals_dilithium2_ref_ntt_label9:15  %add_ln19 = add i56 %sext_ln58_1, %sext_ln19_4

]]></Node>
<StgValue><ssdm name="add_ln19"/></StgValue>
</operation>

<operation id="79" st_id="10" stage="1" lat="1">
<core>NULL</core>
<MemPortIdVec></MemPortIdVec>
<condition id="-1">
<or_exp><and_exp></and_exp></or_exp>
</condition>

<Node id="64" bw="24" op_0_bw="24" op_1_bw="56" op_2_bw="32" op_3_bw="32">
<![CDATA[
pqcrystals_dilithium2_ref_ntt_label9:16  %trunc_ln = call i24 @_ssdm_op_PartSelect.i24.i56.i32.i32(i56 %add_ln19, i32 32, i32 55)

]]></Node>
<StgValue><ssdm name="trunc_ln"/></StgValue>
</operation>

<operation id="80" st_id="10" stage="1" lat="1">
<core>NULL</core>
<MemPortIdVec></MemPortIdVec>
<condition id="-1">
<or_exp><and_exp></and_exp></or_exp>
</condition>

<Node id="65" bw="32" op_0_bw="24">
<![CDATA[
pqcrystals_dilithium2_ref_ntt_label9:17  %t_11 = sext i24 %trunc_ln to i32

]]></Node>
<StgValue><ssdm name="t_11"/></StgValue>
</operation>

<operation id="81" st_id="10" stage="1" lat="2">
<core>RAM</core>
<MemPortIdVec>0 </MemPortIdVec>
<condition id="-1">
<or_exp><and_exp></and_exp></or_exp>
</condition>

<Node id="68" bw="32" op_0_bw="8">
<![CDATA[
pqcrystals_dilithium2_ref_ntt_label9:20  %a_load_6 = load i32* %a_addr_3, align 4

]]></Node>
<StgValue><ssdm name="a_load_6"/></StgValue>
</operation>

<operation id="82" st_id="10" stage="1" lat="1">
<core>AddSub</core>
<MemPortIdVec></MemPortIdVec>
<condition id="-1">
<or_exp><and_exp></and_exp></or_exp>
</condition>

<Node id="69" bw="32" op_0_bw="32" op_1_bw="32">
<![CDATA[
pqcrystals_dilithium2_ref_ntt_label9:21  %sub_ln59 = sub nsw i32 %a_load_6, %t_11

]]></Node>
<StgValue><ssdm name="sub_ln59"/></StgValue>
</operation>

<operation id="83" st_id="10" stage="1" lat="1">
<core>RAM</core>
<MemPortIdVec>0 </MemPortIdVec>
<condition id="-1">
<or_exp><and_exp></and_exp></or_exp>
</condition>

<Node id="70" bw="0" op_0_bw="32" op_1_bw="8" op_2_bw="32" op_3_bw="32">
<![CDATA[
pqcrystals_dilithium2_ref_ntt_label9:22  store i32 %sub_ln59, i32* %a_addr, align 4

]]></Node>
<StgValue><ssdm name="store_ln59"/></StgValue>
</operation>
</state>

<state id="11" st_id="11">

<operation id="84" st_id="11" stage="2" lat="2">
<core>RAM</core>
<MemPortIdVec>0 </MemPortIdVec>
<condition id="-1">
<or_exp><and_exp></and_exp></or_exp>
</condition>

<Node id="71" bw="32" op_0_bw="8" op_1_bw="0">
<![CDATA[
pqcrystals_dilithium2_ref_ntt_label9:23  %a_load_7 = load i32* %a_addr_3, align 4

]]></Node>
<StgValue><ssdm name="a_load_7"/></StgValue>
</operation>
</state>

<state id="12" st_id="12">

<operation id="85" st_id="12" stage="1" lat="1">
<core>NULL</core>
<MemPortIdVec></MemPortIdVec>
<condition id="-1">
<or_exp><and_exp></and_exp></or_exp>
</condition>

<Node id="48" bw="0" op_0_bw="0" op_1_bw="0">
<![CDATA[
pqcrystals_dilithium2_ref_ntt_label9:0  call void (...)* @_ssdm_op_SpecLoopName([37 x i8]* @p_str316) nounwind

]]></Node>
<StgValue><ssdm name="specloopname_ln57"/></StgValue>
</operation>

<operation id="86" st_id="12" stage="1" lat="1">
<core>NULL</core>
<MemPortIdVec></MemPortIdVec>
<condition id="-1">
<or_exp><and_exp></and_exp></or_exp>
</condition>

<Node id="49" bw="32" op_0_bw="32" op_1_bw="0">
<![CDATA[
pqcrystals_dilithium2_ref_ntt_label9:1  %tmp_5 = call i32 (...)* @_ssdm_op_SpecRegionBegin([37 x i8]* @p_str316)

]]></Node>
<StgValue><ssdm name="tmp_5"/></StgValue>
</operation>

<operation id="87" st_id="12" stage="1" lat="1">
<core>NULL</core>
<MemPortIdVec></MemPortIdVec>
<condition id="-1">
<or_exp><and_exp></and_exp></or_exp>
</condition>

<Node id="50" bw="0" op_0_bw="0" op_1_bw="32" op_2_bw="32" op_3_bw="32" op_4_bw="0">
<![CDATA[
pqcrystals_dilithium2_ref_ntt_label9:2  call void (...)* @_ssdm_op_SpecLoopTripCount(i32 0, i32 128, i32 64, [1 x i8]* @p_str114) nounwind

]]></Node>
<StgValue><ssdm name="speclooptripcount_ln58"/></StgValue>
</operation>

<operation id="88" st_id="12" stage="1" lat="2">
<core>RAM</core>
<MemPortIdVec>0 </MemPortIdVec>
<condition id="-1">
<or_exp><and_exp></and_exp></or_exp>
</condition>

<Node id="71" bw="32" op_0_bw="8" op_1_bw="0">
<![CDATA[
pqcrystals_dilithium2_ref_ntt_label9:23  %a_load_7 = load i32* %a_addr_3, align 4

]]></Node>
<StgValue><ssdm name="a_load_7"/></StgValue>
</operation>

<operation id="89" st_id="12" stage="1" lat="1">
<core>AddSub</core>
<MemPortIdVec></MemPortIdVec>
<condition id="-1">
<or_exp><and_exp></and_exp></or_exp>
</condition>

<Node id="72" bw="32" op_0_bw="32" op_1_bw="32">
<![CDATA[
pqcrystals_dilithium2_ref_ntt_label9:24  %add_ln60 = add nsw i32 %t_11, %a_load_7

]]></Node>
<StgValue><ssdm name="add_ln60"/></StgValue>
</operation>

<operation id="90" st_id="12" stage="1" lat="1">
<core>RAM</core>
<MemPortIdVec>0 </MemPortIdVec>
<condition id="-1">
<or_exp><and_exp></and_exp></or_exp>
</condition>

<Node id="73" bw="0" op_0_bw="32" op_1_bw="8" op_2_bw="32">
<![CDATA[
pqcrystals_dilithium2_ref_ntt_label9:25  store i32 %add_ln60, i32* %a_addr_3, align 4

]]></Node>
<StgValue><ssdm name="store_ln60"/></StgValue>
</operation>

<operation id="91" st_id="12" stage="1" lat="1">
<core>NULL</core>
<MemPortIdVec></MemPortIdVec>
<condition id="-1">
<or_exp><and_exp></and_exp></or_exp>
</condition>

<Node id="74" bw="32" op_0_bw="32" op_1_bw="0" op_2_bw="32">
<![CDATA[
pqcrystals_dilithium2_ref_ntt_label9:26  %empty_31 = call i32 (...)* @_ssdm_op_SpecRegionEnd([37 x i8]* @p_str316, i32 %tmp_5)

]]></Node>
<StgValue><ssdm name="empty_31"/></StgValue>
</operation>

<operation id="92" st_id="12" stage="1" lat="1">
<core>NULL</core>
<MemPortIdVec></MemPortIdVec>
<condition id="-1">
<or_exp><and_exp></and_exp></or_exp>
</condition>

<Node id="76" bw="0" op_0_bw="0">
<![CDATA[
pqcrystals_dilithium2_ref_ntt_label9:28  br label %3

]]></Node>
<StgValue><ssdm name="br_ln57"/></StgValue>
</operation>
</state>
</state_list>


<ports>
<port id="109" name="a" dir="2" iftype="1">
<core>RAM</core><StgValue><ssdm name="a"/><MemPortTyVec>2 3 </MemPortTyVec>
</StgValue>
</port>
<port id="110" name="zetas" dir="0" iftype="1">
<core>ROM_nP</core><StgValue><ssdm name="zetas"/><MemPortTyVec>1 </MemPortTyVec>
</StgValue>
</port>
</ports>


<dataflows>
<dataflow id="112" from="StgValue_111" to="k_3" fromId="111" toId="13">
</dataflow>
<dataflow id="114" from="StgValue_113" to="store_ln54" fromId="113" toId="14">
</dataflow>
<dataflow id="115" from="k_3" to="store_ln54" fromId="13" toId="14">
</dataflow>
<dataflow id="117" from="StgValue_116" to="len_0" fromId="116" toId="16">
<condition id="-1">
<or_exp><and_exp></and_exp></or_exp>
</condition>
</dataflow>
<dataflow id="118" from="br_ln54" to="len_0" fromId="15" toId="16">
</dataflow>
<dataflow id="119" from="zext_ln54_3" to="len_0" fromId="38" toId="16">
<BackEdge/>
<condition id="-1">
<or_exp><and_exp><literal name="icmp_ln55" val="0"/>
</and_exp></or_exp>
</condition>
</dataflow>
<dataflow id="120" from="br_ln54" to="len_0" fromId="39" toId="16">
<BackEdge/>
</dataflow>
<dataflow id="121" from="len_0" to="icmp_ln54" fromId="16" toId="17">
</dataflow>
<dataflow id="123" from="StgValue_122" to="icmp_ln54" fromId="122" toId="17">
</dataflow>
<dataflow id="125" from="_ssdm_op_SpecLoopTripCount" to="speclooptripcount_ln0" fromId="124" toId="18">
</dataflow>
<dataflow id="127" from="StgValue_126" to="speclooptripcount_ln0" fromId="126" toId="18">
</dataflow>
<dataflow id="128" from="StgValue_126" to="speclooptripcount_ln0" fromId="126" toId="18">
</dataflow>
<dataflow id="129" from="StgValue_126" to="speclooptripcount_ln0" fromId="126" toId="18">
</dataflow>
<dataflow id="130" from="icmp_ln54" to="br_ln54" fromId="17" toId="19">
</dataflow>
<dataflow id="131" from="len_0" to="zext_ln54" fromId="16" toId="20">
</dataflow>
<dataflow id="132" from="len_0" to="zext_ln54_2" fromId="16" toId="21">
</dataflow>
<dataflow id="134" from="_ssdm_op_SpecLoopName" to="specloopname_ln54" fromId="133" toId="22">
</dataflow>
<dataflow id="136" from="p_str13" to="specloopname_ln54" fromId="135" toId="22">
</dataflow>
<dataflow id="138" from="_ssdm_op_SpecRegionBegin" to="tmp" fromId="137" toId="23">
</dataflow>
<dataflow id="139" from="p_str13" to="tmp" fromId="135" toId="23">
</dataflow>
<dataflow id="141" from="StgValue_140" to="j" fromId="140" toId="26">
<condition id="-1">
<or_exp><and_exp><literal name="icmp_ln54" val="0"/>
</and_exp></or_exp>
</condition>
</dataflow>
<dataflow id="142" from="br_ln55" to="j" fromId="24" toId="26">
</dataflow>
<dataflow id="143" from="add_ln55" to="j" fromId="65" toId="26">
<BackEdge/>
<condition id="-1">
<or_exp><and_exp><literal name="icmp_ln57" val="0"/>
</and_exp></or_exp>
</condition>
</dataflow>
<dataflow id="144" from="br_ln55" to="j" fromId="67" toId="26">
<BackEdge/>
</dataflow>
<dataflow id="145" from="j" to="zext_ln55" fromId="26" toId="27">
</dataflow>
<dataflow id="147" from="_ssdm_op_PartSelect.i23.i31.i32.i32" to="tmp_8" fromId="146" toId="28">
</dataflow>
<dataflow id="148" from="j" to="tmp_8" fromId="26" toId="28">
</dataflow>
<dataflow id="150" from="StgValue_149" to="tmp_8" fromId="149" toId="28">
</dataflow>
<dataflow id="152" from="StgValue_151" to="tmp_8" fromId="151" toId="28">
</dataflow>
<dataflow id="153" from="tmp_8" to="icmp_ln55" fromId="28" toId="29">
</dataflow>
<dataflow id="155" from="StgValue_154" to="icmp_ln55" fromId="154" toId="29">
</dataflow>
<dataflow id="156" from="icmp_ln55" to="br_ln55" fromId="29" toId="30">
</dataflow>
<dataflow id="157" from="k_3" to="k_3_load" fromId="13" toId="31">
</dataflow>
<dataflow id="158" from="StgValue_111" to="k" fromId="111" toId="32">
</dataflow>
<dataflow id="159" from="k_3_load" to="k" fromId="31" toId="32">
</dataflow>
<dataflow id="160" from="k" to="zext_ln56" fromId="32" toId="33">
</dataflow>
<dataflow id="161" from="zetas" to="zetas_addr" fromId="110" toId="34">
</dataflow>
<dataflow id="163" from="StgValue_162" to="zetas_addr" fromId="162" toId="34">
</dataflow>
<dataflow id="164" from="zext_ln56" to="zetas_addr" fromId="33" toId="34">
</dataflow>
<dataflow id="165" from="zetas_addr" to="zeta" fromId="34" toId="35">
</dataflow>
<dataflow id="167" from="_ssdm_op_SpecRegionEnd" to="empty_33" fromId="166" toId="36">
</dataflow>
<dataflow id="168" from="p_str13" to="empty_33" fromId="135" toId="36">
</dataflow>
<dataflow id="169" from="tmp" to="empty_33" fromId="23" toId="36">
</dataflow>
<dataflow id="171" from="_ssdm_op_PartSelect.i28.i29.i32.i32" to="tmp_9" fromId="170" toId="37">
</dataflow>
<dataflow id="172" from="len_0" to="tmp_9" fromId="16" toId="37">
</dataflow>
<dataflow id="173" from="StgValue_111" to="tmp_9" fromId="111" toId="37">
</dataflow>
<dataflow id="175" from="StgValue_174" to="tmp_9" fromId="174" toId="37">
</dataflow>
<dataflow id="176" from="tmp_9" to="zext_ln54_3" fromId="37" toId="38">
</dataflow>
<dataflow id="177" from="_ssdm_op_SpecLoopName" to="specloopname_ln55" fromId="133" toId="40">
</dataflow>
<dataflow id="179" from="p_str215" to="specloopname_ln55" fromId="178" toId="40">
</dataflow>
<dataflow id="180" from="_ssdm_op_SpecRegionBegin" to="tmp_s" fromId="137" toId="41">
</dataflow>
<dataflow id="181" from="p_str215" to="tmp_s" fromId="178" toId="41">
</dataflow>
<dataflow id="182" from="_ssdm_op_SpecLoopTripCount" to="speclooptripcount_ln56" fromId="124" toId="42">
</dataflow>
<dataflow id="183" from="StgValue_113" to="speclooptripcount_ln56" fromId="113" toId="42">
</dataflow>
<dataflow id="185" from="StgValue_184" to="speclooptripcount_ln56" fromId="184" toId="42">
</dataflow>
<dataflow id="187" from="StgValue_186" to="speclooptripcount_ln56" fromId="186" toId="42">
</dataflow>
<dataflow id="189" from="p_str114" to="speclooptripcount_ln56" fromId="188" toId="42">
</dataflow>
<dataflow id="191" from="_ssdm_op_SpecPipeline" to="specpipeline_ln56" fromId="190" toId="43">
</dataflow>
<dataflow id="193" from="StgValue_192" to="specpipeline_ln56" fromId="192" toId="43">
</dataflow>
<dataflow id="194" from="StgValue_111" to="specpipeline_ln56" fromId="111" toId="43">
</dataflow>
<dataflow id="195" from="StgValue_111" to="specpipeline_ln56" fromId="111" toId="43">
</dataflow>
<dataflow id="196" from="StgValue_113" to="specpipeline_ln56" fromId="113" toId="43">
</dataflow>
<dataflow id="197" from="p_str114" to="specpipeline_ln56" fromId="188" toId="43">
</dataflow>
<dataflow id="198" from="zetas_addr" to="zeta" fromId="34" toId="44">
</dataflow>
<dataflow id="199" from="zext_ln54_2" to="add_ln57" fromId="21" toId="45">
</dataflow>
<dataflow id="200" from="j" to="add_ln57" fromId="26" toId="45">
</dataflow>
<dataflow id="201" from="add_ln57" to="zext_ln57" fromId="45" toId="46">
</dataflow>
<dataflow id="202" from="j" to="empty" fromId="26" toId="47">
</dataflow>
<dataflow id="203" from="add_ln57" to="empty" fromId="45" toId="47">
</dataflow>
<dataflow id="204" from="j" to="trunc_ln55" fromId="26" toId="48">
</dataflow>
<dataflow id="205" from="add_ln57" to="trunc_ln55_2" fromId="45" toId="49">
</dataflow>
<dataflow id="206" from="empty" to="start" fromId="47" toId="50">
</dataflow>
<dataflow id="207" from="trunc_ln55" to="start" fromId="48" toId="50">
</dataflow>
<dataflow id="208" from="trunc_ln55_2" to="start" fromId="49" toId="50">
</dataflow>
<dataflow id="209" from="start" to="zext_ln55_2" fromId="50" toId="51">
</dataflow>
<dataflow id="210" from="zeta" to="sext_ln57" fromId="44" toId="52">
</dataflow>
<dataflow id="211" from="zext_ln55" to="j_0" fromId="27" toId="54">
<condition id="-1">
<or_exp><and_exp></and_exp></or_exp>
</condition>
</dataflow>
<dataflow id="212" from="br_ln57" to="j_0" fromId="53" toId="54">
</dataflow>
<dataflow id="213" from="j_5" to="j_0" fromId="63" toId="54">
<BackEdge/>
<condition id="-1">
<or_exp><and_exp></and_exp></or_exp>
</condition>
</dataflow>
<dataflow id="214" from="br_ln57" to="j_0" fromId="92" toId="54">
<BackEdge/>
</dataflow>
<dataflow id="215" from="j_0" to="icmp_ln57" fromId="54" toId="55">
</dataflow>
<dataflow id="216" from="zext_ln57" to="icmp_ln57" fromId="46" toId="55">
</dataflow>
<dataflow id="217" from="icmp_ln57" to="br_ln57" fromId="55" toId="56">
</dataflow>
<dataflow id="218" from="zext_ln54" to="add_ln58" fromId="20" toId="57">
</dataflow>
<dataflow id="219" from="j_0" to="add_ln58" fromId="54" toId="57">
</dataflow>
<dataflow id="220" from="add_ln58" to="zext_ln58" fromId="57" toId="58">
</dataflow>
<dataflow id="221" from="a" to="a_addr" fromId="109" toId="59">
</dataflow>
<dataflow id="222" from="StgValue_162" to="a_addr" fromId="162" toId="59">
</dataflow>
<dataflow id="223" from="zext_ln58" to="a_addr" fromId="58" toId="59">
</dataflow>
<dataflow id="224" from="a_addr" to="a_load" fromId="59" toId="60">
</dataflow>
<dataflow id="225" from="j_0" to="zext_ln59" fromId="54" toId="61">
</dataflow>
<dataflow id="226" from="a" to="a_addr_3" fromId="109" toId="62">
</dataflow>
<dataflow id="227" from="StgValue_162" to="a_addr_3" fromId="162" toId="62">
</dataflow>
<dataflow id="228" from="zext_ln59" to="a_addr_3" fromId="61" toId="62">
</dataflow>
<dataflow id="229" from="StgValue_111" to="j_5" fromId="111" toId="63">
</dataflow>
<dataflow id="230" from="j_0" to="j_5" fromId="54" toId="63">
</dataflow>
<dataflow id="231" from="_ssdm_op_SpecRegionEnd" to="empty_32" fromId="166" toId="64">
</dataflow>
<dataflow id="232" from="p_str215" to="empty_32" fromId="178" toId="64">
</dataflow>
<dataflow id="233" from="tmp_s" to="empty_32" fromId="41" toId="64">
</dataflow>
<dataflow id="234" from="zext_ln54_2" to="add_ln55" fromId="21" toId="65">
</dataflow>
<dataflow id="235" from="zext_ln55_2" to="add_ln55" fromId="51" toId="65">
</dataflow>
<dataflow id="236" from="k" to="store_ln55" fromId="32" toId="66">
</dataflow>
<dataflow id="237" from="k_3" to="store_ln55" fromId="13" toId="66">
</dataflow>
<dataflow id="238" from="a_addr" to="a_load" fromId="59" toId="68">
</dataflow>
<dataflow id="239" from="a_load" to="sext_ln58" fromId="68" toId="69">
</dataflow>
<dataflow id="240" from="sext_ln57" to="mul_ln58" fromId="52" toId="70">
</dataflow>
<dataflow id="241" from="sext_ln58" to="mul_ln58" fromId="69" toId="70">
</dataflow>
<dataflow id="242" from="mul_ln58" to="trunc_ln18" fromId="70" toId="71">
</dataflow>
<dataflow id="244" from="StgValue_243" to="t" fromId="243" toId="72">
</dataflow>
<dataflow id="245" from="trunc_ln18" to="t" fromId="71" toId="72">
</dataflow>
<dataflow id="246" from="t" to="sext_ln19" fromId="72" toId="73">
</dataflow>
<dataflow id="248" from="StgValue_247" to="mul_ln19" fromId="247" toId="74">
</dataflow>
<dataflow id="249" from="sext_ln19" to="mul_ln19" fromId="73" toId="74">
</dataflow>
<dataflow id="250" from="a_addr_3" to="a_load_6" fromId="62" toId="75">
</dataflow>
<dataflow id="251" from="mul_ln58" to="sext_ln58_1" fromId="70" toId="76">
</dataflow>
<dataflow id="252" from="mul_ln19" to="sext_ln19_4" fromId="74" toId="77">
</dataflow>
<dataflow id="253" from="sext_ln58_1" to="add_ln19" fromId="76" toId="78">
</dataflow>
<dataflow id="254" from="sext_ln19_4" to="add_ln19" fromId="77" toId="78">
</dataflow>
<dataflow id="256" from="_ssdm_op_PartSelect.i24.i56.i32.i32" to="trunc_ln" fromId="255" toId="79">
</dataflow>
<dataflow id="257" from="add_ln19" to="trunc_ln" fromId="78" toId="79">
</dataflow>
<dataflow id="259" from="StgValue_258" to="trunc_ln" fromId="258" toId="79">
</dataflow>
<dataflow id="261" from="StgValue_260" to="trunc_ln" fromId="260" toId="79">
</dataflow>
<dataflow id="262" from="trunc_ln" to="t_11" fromId="79" toId="80">
</dataflow>
<dataflow id="263" from="a_addr_3" to="a_load_6" fromId="62" toId="81">
</dataflow>
<dataflow id="264" from="a_load_6" to="sub_ln59" fromId="81" toId="82">
</dataflow>
<dataflow id="265" from="t_11" to="sub_ln59" fromId="80" toId="82">
</dataflow>
<dataflow id="266" from="sub_ln59" to="store_ln59" fromId="82" toId="83">
</dataflow>
<dataflow id="267" from="a_addr" to="store_ln59" fromId="59" toId="83">
</dataflow>
<dataflow id="268" from="a_addr_3" to="a_load_7" fromId="62" toId="84">
</dataflow>
<dataflow id="269" from="_ssdm_op_SpecLoopName" to="specloopname_ln57" fromId="133" toId="85">
</dataflow>
<dataflow id="271" from="p_str316" to="specloopname_ln57" fromId="270" toId="85">
</dataflow>
<dataflow id="272" from="_ssdm_op_SpecRegionBegin" to="tmp_5" fromId="137" toId="86">
</dataflow>
<dataflow id="273" from="p_str316" to="tmp_5" fromId="270" toId="86">
</dataflow>
<dataflow id="274" from="_ssdm_op_SpecLoopTripCount" to="speclooptripcount_ln58" fromId="124" toId="87">
</dataflow>
<dataflow id="275" from="StgValue_113" to="speclooptripcount_ln58" fromId="113" toId="87">
</dataflow>
<dataflow id="276" from="StgValue_186" to="speclooptripcount_ln58" fromId="186" toId="87">
</dataflow>
<dataflow id="278" from="StgValue_277" to="speclooptripcount_ln58" fromId="277" toId="87">
</dataflow>
<dataflow id="279" from="p_str114" to="speclooptripcount_ln58" fromId="188" toId="87">
</dataflow>
<dataflow id="280" from="a_addr_3" to="a_load_7" fromId="62" toId="88">
</dataflow>
<dataflow id="281" from="t_11" to="add_ln60" fromId="80" toId="89">
</dataflow>
<dataflow id="282" from="a_load_7" to="add_ln60" fromId="88" toId="89">
</dataflow>
<dataflow id="283" from="add_ln60" to="store_ln60" fromId="89" toId="90">
</dataflow>
<dataflow id="284" from="a_addr_3" to="store_ln60" fromId="62" toId="90">
</dataflow>
<dataflow id="285" from="_ssdm_op_SpecRegionEnd" to="empty_31" fromId="166" toId="91">
</dataflow>
<dataflow id="286" from="p_str316" to="empty_31" fromId="270" toId="91">
</dataflow>
<dataflow id="287" from="tmp_5" to="empty_31" fromId="86" toId="91">
</dataflow>
<dataflow id="288" from="icmp_ln54" to="StgValue_2" fromId="17" toId="2">
</dataflow>
<dataflow id="289" from="icmp_ln55" to="StgValue_3" fromId="29" toId="3">
</dataflow>
<dataflow id="290" from="icmp_ln57" to="StgValue_5" fromId="55" toId="5">
</dataflow>
</dataflows>


</stg>
